communauto/__init__.py
communauto/grammar.lark
communauto-0.1.6.dist-info/entry_points.txt
communauto-0.1.6.dist-info/LICENSE
communauto-0.1.6.dist-info/WHEEL
communauto-0.1.6.dist-info/METADATA
communauto-0.1.6.dist-info/RECORD
